{
  "/src/curl_fuzzer": {
    "type": "git",
    "url": "https://github.com/curl/curl-fuzzer.git",
    "rev": "543b9926cc322a18ad30945dc55d78dbbfa679e1"
  },
  "/src/curl": {
    "type": "git",
    "url": "https://github.com/curl/curl.git",
    "rev": "485c9ba50a0bc55314b6f36c50550a0502ee4e4b"
  },
  "/src/centipede": {
    "type": "git",
    "url": "https://github.com/google/centipede.git",
    "rev": "f29cab3bbe2dc1cf2661e74b6a85214bd23194cb"
  },
  "/src/aflplusplus": {
    "type": "git",
    "url": "https://github.com/AFLplusplus/AFLplusplus.git",
    "rev": "c208dcf9c573e3d85990c7dea777646f7fa4961c"
  }
}
