{
  "/src/jbigkit": {
    "type": "git",
    "url": "https://www.cl.cam.ac.uk/~mgk25/git/jbigkit",
    "rev": "7d3c1bea895d910907e2501fe9165e353eceabae"
  },
  "/src/libjxl": {
    "type": "git",
    "url": "https://github.com/libjxl/libjxl.git",
    "rev": "798512a9e83c5b36d4e6a097c11bf122d30c1b8f"
  },
  "/src/libzip": {
    "type": "git",
    "url": "https://github.com/nih-at/libzip.git",
    "rev": "e9083a7b41463489cd6641310c36f3b9197e1d27"
  },
  "/src/libxml2": {
    "type": "git",
    "url": "https://gitlab.gnome.org/GNOME/libxml2.git",
    "rev": "ee0eda4b12ae476905c4a265dc9a190ad76bc7b2"
  },
  "/src/jasper": {
    "type": "git",
    "url": "https://github.com/jasper-software/jasper",
    "rev": "8766848706a727f61c1c76a5a7cf1078433fad02"
  },
  "/src/bzip2": {
    "type": "git",
    "url": "https://gitlab.com/federicomenaquintero/bzip2.git",
    "rev": "bf905ea2251191ff9911ae7ec0cfc35d41f9f7f6"
  },
  "/src/Little-CMS": {
    "type": "git",
    "url": "https://github.com/mm2/Little-CMS",
    "rev": "fab0275daa910aa422535bdffb76926481d5f4d5"
  },
  "/src/libpng": {
    "type": "git",
    "url": "https://github.com/pnggroup/libpng",
    "rev": "34005e3d3d373c0c36898cc55eae48a79c8238a1"
  },
  "/src/freetype": {
    "type": "git",
    "url": "https://github.com/freetype/freetype",
    "rev": "5d4e649f740c675426fbe4cdaffc53ee2a4cb954"
  },
  "/src/libjpeg-turbo": {
    "type": "git",
    "url": "https://github.com/libjpeg-turbo/libjpeg-turbo",
    "rev": "adbb328159b5558e846690c49f9458deccbb0f43"
  },
  "/src/zstd": {
    "type": "git",
    "url": "https://github.com/facebook/zstd",
    "rev": "eca205fc7849a61ab287492931a04960ac58e031"
  },
  "/src/xz": {
    "type": "git",
    "url": "https://github.com/tukaani-project/xz",
    "rev": "48053c90898fa191a216aefca01626520a7413f4"
  },
  "/src/zlib": {
    "type": "git",
    "url": "https://github.com/madler/zlib",
    "rev": "5a82f71ed1dfc0bec044d9702463dbdf84ea3b71"
  },
  "/src/libwebp": {
    "type": "git",
    "url": "https://github.com/webmproject/libwebp",
    "rev": "1d86819f49edc8237fa2b844543081bcb8ef8a92"
  },
  "/src/libheif": {
    "type": "git",
    "url": "https://github.com/strukturag/libheif",
    "rev": "8531ee0eae8145a73569bafd16b038dd474cc59a"
  },
  "/src/openjpeg": {
    "type": "git",
    "url": "https://github.com/uclouvain/openjpeg",
    "rev": "e7453e398b110891778d8da19209792c69ca7169"
  },
  "/src/openh264": {
    "type": "git",
    "url": "https://github.com/cisco/openh264",
    "rev": "c2e7c4a3b9bfc767b83631cc9bdfb17bfd2705c6"
  },
  "/src/aom": {
    "type": "git",
    "url": "https://aomedia.googlesource.com/aom",
    "rev": "402e264b94fd74bdf66837da216b6251805b4ae4"
  },
  "/src/x265": {
    "type": "git",
    "url": "https://bitbucket.org/multicoreware/x265_git/src/stable/",
    "rev": "ef83e1285847952bd50c04cfe98bd521845f05db"
  },
  "/src/libde265": {
    "type": "git",
    "url": "https://github.com/strukturag/libde265",
    "rev": "b67f401c373f182a426a2d79e77e66f9277981da"
  },
  "/src/libtiff": {
    "type": "git",
    "url": "https://gitlab.com/libtiff/libtiff",
    "rev": "1d277003a0c5c7f5691d1dc8164f7a31d39f0925"
  },
  "/src/graphicsmagick": {
    "type": "hg",
    "url": "https://foss.heptapod.net/graphicsmagick/graphicsmagick",
    "rev": "036a1376a2a6dc9504c5148249cbd8feaef72de6"
  }
}
