{
  "/src/libpcap": {
    "type": "git",
    "url": "https://github.com/the-tcpdump-group/libpcap.git",
    "rev": "7b8c17a8ea76e7df7dce5c15dc6864505e9e66ac"
  },
  "/src/tcpdump": {
    "type": "git",
    "url": "https://github.com/the-tcpdump-group/tcpdump.git",
    "rev": "50fab58b36c49137d428e050f25f555657642943"
  },
  "/src/PcapPlusPlus": {
    "type": "git",
    "url": "https://github.com/seladb/PcapPlusPlus",
    "rev": "0376f65957378c9235f9f094cec7c655ab836f15"
  },
  "/src/afl": {
    "type": "git",
    "url": "https://github.com/google/AFL.git",
    "rev": "8da80951dd7eeeb3e3b5a3bcd36c485045f40274"
  }
}
