{
  "/src/jbigkit": {
    "type": "git",
    "url": "https://www.cl.cam.ac.uk/~mgk25/git/jbigkit",
    "rev": "7d3c1bea895d910907e2501fe9165e353eceabae"
  },
  "/src/libjxl": {
    "type": "git",
    "url": "https://github.com/libjxl/libjxl.git",
    "rev": "798512a9e83c5b36d4e6a097c11bf122d30c1b8f"
  },
  "/src/libzip": {
    "type": "git",
    "url": "https://github.com/nih-at/libzip.git",
    "rev": "e9083a7b41463489cd6641310c36f3b9197e1d27"
  },
  "/src/libxml2": {
    "type": "git",
    "url": "https://gitlab.gnome.org/GNOME/libxml2.git",
    "rev": "dd4c0f62fa1fd9650aae6b718dd9964a4ffa69b9"
  },
  "/src/jasper": {
    "type": "git",
    "url": "https://github.com/jasper-software/jasper",
    "rev": "849888f0a6e76bb440581d5f8c0a947a39e92aa2"
  },
  "/src/bzip2": {
    "type": "git",
    "url": "https://gitlab.com/federicomenaquintero/bzip2.git",
    "rev": "bf905ea2251191ff9911ae7ec0cfc35d41f9f7f6"
  },
  "/src/Little-CMS": {
    "type": "git",
    "url": "https://github.com/mm2/Little-CMS",
    "rev": "fab0275daa910aa422535bdffb76926481d5f4d5"
  },
  "/src/libpng": {
    "type": "git",
    "url": "https://github.com/pnggroup/libpng",
    "rev": "34005e3d3d373c0c36898cc55eae48a79c8238a1"
  },
  "/src/freetype": {
    "type": "git",
    "url": "https://github.com/freetype/freetype",
    "rev": "82090e67c24259c343c83fd9cefe6ff0be7a7eca"
  },
  "/src/libjpeg-turbo": {
    "type": "git",
    "url": "https://github.com/libjpeg-turbo/libjpeg-turbo",
    "rev": "adbb328159b5558e846690c49f9458deccbb0f43"
  },
  "/src/zstd": {
    "type": "git",
    "url": "https://github.com/facebook/zstd",
    "rev": "12ea5f6e30c5b0411dd39d29089b5ee4e0044403"
  },
  "/src/xz": {
    "type": "git",
    "url": "https://github.com/tukaani-project/xz",
    "rev": "173fb5c68b08a8c1369550267be258132b7760c6"
  },
  "/src/zlib": {
    "type": "git",
    "url": "https://github.com/madler/zlib",
    "rev": "5a82f71ed1dfc0bec044d9702463dbdf84ea3b71"
  },
  "/src/libwebp": {
    "type": "git",
    "url": "https://github.com/webmproject/libwebp",
    "rev": "7c70ff7a3b81fbdac7ee138836743b2802e247d4"
  },
  "/src/libheif": {
    "type": "git",
    "url": "https://github.com/strukturag/libheif",
    "rev": "e2253ec2339896868ae37739367d6b59be2e2d1e"
  },
  "/src/openjpeg": {
    "type": "git",
    "url": "https://github.com/uclouvain/openjpeg",
    "rev": "e7453e398b110891778d8da19209792c69ca7169"
  },
  "/src/openh264": {
    "type": "git",
    "url": "https://github.com/cisco/openh264",
    "rev": "c2e7c4a3b9bfc767b83631cc9bdfb17bfd2705c6"
  },
  "/src/aom": {
    "type": "git",
    "url": "https://aomedia.googlesource.com/aom",
    "rev": "402e264b94fd74bdf66837da216b6251805b4ae4"
  },
  "/src/x265": {
    "type": "git",
    "url": "https://bitbucket.org/multicoreware/x265_git/src/stable/",
    "rev": "b354c009a60bcd6d7fc04014e200a1ee9c45c167"
  },
  "/src/libde265": {
    "type": "git",
    "url": "https://github.com/strukturag/libde265",
    "rev": "b67f401c373f182a426a2d79e77e66f9277981da"
  },
  "/src/libtiff": {
    "type": "git",
    "url": "https://gitlab.com/libtiff/libtiff",
    "rev": "8164e15eec5098716fcc3c972e933787fda418aa"
  },
  "/src/graphicsmagick": {
    "type": "hg",
    "url": "https://foss.heptapod.net/graphicsmagick/graphicsmagick",
    "rev": "8e56520435df50f618a03f2721a39a70a515f1cb"
  }
}
