{
  "/src/libpcap": {
    "type": "git",
    "url": "https://github.com/the-tcpdump-group/libpcap.git",
    "rev": "080d63db2f566ad6378069ca24359f3c635cc6e3"
  },
  "/src/tcpdump": {
    "type": "git",
    "url": "https://github.com/the-tcpdump-group/tcpdump.git",
    "rev": "afb355923c6d4e35a86e89de405545fc1481fcac"
  },
  "/src/PcapPlusPlus": {
    "type": "git",
    "url": "https://github.com/seladb/PcapPlusPlus",
    "rev": "c7bce23c8ce9ca3d30352f2b3c463b6b18b62453"
  },
  "/src/afl": {
    "type": "git",
    "url": "https://github.com/google/AFL.git",
    "rev": "82b5e359463238d790cadbe2dd494d6a4928bff3"
  }
}
