{
  "/src/qt/qtqa": {
    "type": "git",
    "url": "git://code.qt.io/qt/qtqa.git",
    "rev": "c2586b65d39a35cc57180beb5021ca5ebd8f1eb0"
  },
  "/src/qt/qtsvg": {
    "type": "git",
    "url": "git://code.qt.io/qt/qtsvg.git",
    "rev": "c74d930ee01e8566b5e5802a18f85a8703c7c90e"
  },
  "/src/qt/qtbase": {
    "type": "git",
    "url": "git://code.qt.io/qt/qtbase.git",
    "rev": "baffc8e47df15190cd85705099698a72e2bdbfa0"
  },
  "/src/qt/qtimageformats": {
    "type": "git",
    "url": "git://code.qt.io/qt/qtimageformats.git",
    "rev": "76344f084318cdd44ca5b77778ac350cc13e9d7a"
  }
}
